LICENSE
README.md
setup.cfg
setup.py
eventslib/__init__.py
eventslib/events.py
eventslib.egg-info/PKG-INFO
eventslib.egg-info/SOURCES.txt
eventslib.egg-info/dependency_links.txt
eventslib.egg-info/not-zip-safe
eventslib.egg-info/top_level.txt