Metadata-Version: 1.0
Name: eventslib
Version: 0.0
Summary: Tiny python event library for my projects
Home-page: UNKNOWN
Author: UNKNOWN
Author-email: UNKNOWN
License: UNKNOWN
Platform: UNKNOWN
